jupyterlab_gitlab.py
jupyterlab_gitlab_msg-2.0.4.data/data/etc/jupyter/jupyter_notebook_config.d/jupyterlab_gitlab.json
jupyterlab_gitlab_msg-2.0.4.dist-info/LICENSE
jupyterlab_gitlab_msg-2.0.4.dist-info/METADATA
jupyterlab_gitlab_msg-2.0.4.dist-info/WHEEL
jupyterlab_gitlab_msg-2.0.4.dist-info/top_level.txt
jupyterlab_gitlab_msg-2.0.4.dist-info/RECORD
