Metadata-Version: 2.1
Name: jupyterlab-gitlab-msg
Version: 2.0.4
Summary: A Jupyter Notebook server extension which acts as a proxy for the GitLab API.
Home-page: https://gitlab.com/enki-portal/jupyterlab-gitlab
Author: Benjamin Bertrand
Author-email: beenje@gmail.com
License: BSD
Keywords: Jupyter,JupyterLab,GitLab
Platform: Linux
Platform: Mac OS X
Platform: Windows
Classifier: Intended Audience :: Developers
Classifier: Intended Audience :: System Administrators
Classifier: Intended Audience :: Science/Research
Classifier: License :: OSI Approved :: BSD License
Classifier: Programming Language :: Python
Classifier: Programming Language :: Python :: 3
Requires-Python: >=3.5
Requires-Dist: notebook
